{
  "page_content": "Formerly: ENGL378C.\n\nENGL358 Special Topics in U.S. Latinx Literature (3 Credits) Topical study of selected works by U.S. Latinx writers. Repeatable to: 9 credits if content differs.\n\n2025-2026 [updated 2025.04.17]\n\n190 ENGL - English\n\nENGL359 Special Topics in LGBTQ+ Literatures and Media (3 Credits) Selected study of a topic pertinent to literary and cultural expressions of LGBTQ+ identities, positionalities, and analytics through an exploration of literature, art, and/or media.\n\nCross-listed with: LGBT359.\n\nRepeatable to: 9 credits if content differs.",
  "metadata": {
    "source": "data/2025-2026 Academic Catalog.pdf",
    "doc_type": "pdf",
    "page": 189,
    "section": "",
    "file_hash": "14dada9f1bab",
    "parent_id": "02d6401a-17a4-5e84-866d-fd4f149d4bd5"
  }
}