{
  "page_content": "Prerequisite: ENTS640.\n\nRestriction: Must be in Telecommunications (Master's) program.\n\nENTS649 Special Topics in Networking (3 Credits) Selected topics of current importance in networking. Restriction: Must be in Telecommunications (Master's) program.\n\nENTS653 AWS/PCS System Implementation (3 Credits)\n\nEngineering issues associated with designing and deploying a AWS/ PCS cellular wireless communications system in the current world environment will be examined. The course will focus on implementation issues such as the impact of real world concerns on the deployment\n\nstrategy and the use of good engineering practice to overcome obstacles.\n\nStudents will create and modify mock deployments using professional tools for cell planning and interference analysis. Students will also be exposed to drive testing tools and concepts for migration to future technologies.",
  "metadata": {
    "source": "data/2025-2026 Academic Catalog.pdf",
    "doc_type": "pdf",
    "page": 701,
    "section": "",
    "file_hash": "14dada9f1bab",
    "parent_id": "0eb1502c-1c47-57ec-80b5-880b33e37e09"
  }
}