{
  "page_content": "ENMA621 Advanced Design Composite Materials (3 Credits) Fundamentals of design, processing, and selection of composite materials for structural applications are covered. The topics include a review of all classes of engineering materials, an in-depth analysis of micro and macro mechanical behavior including interactions at the two-phase interfaces, modeling of composite morphologies for optimal microstructures, material aspects, cost considerations, processing methods- including consideration of chemical reactions, stability of the interfaces and material selection. Restriction: Permission of ENGR-Materials Science & Engineering department. Credit Only Granted for: ENMA621 or ENMA698A. Formerly: ENMA698A.\n\nCourses in 2025-2026 Academic Catalog - DRAFT COPY\n\nENMA624 Radiation Engineering (3 Credits) Ionizing radiation, radiation dosimetry and sensors, radiation processing, radiation effects on ; polymers, metals, semiconductors, liquid, and gas, radiation in advance manufacturing, radiation-physical technology. Restriction: Permission of ENGR-Materials Science & Engineering department. Credit Only Granted for: ENMA624 or ENMA698E. Formerly: ENMA698E.",
  "metadata": {
    "source": "data/2025-2026 Academic Catalog.pdf",
    "doc_type": "pdf",
    "page": 670,
    "section": "",
    "file_hash": "14dada9f1bab",
    "parent_id": "1140a6ab-00bb-5803-b7b2-bc18619e7a7d"
  }
}