{
  "page_content": "CMSC715 Wireless and Mobile Systems for the loT (3 Credits)\n\nResearch on the Internet of Things (loT), from the perspective of wireless networking and mobile sensing. Various techniques, algorithms, and systems that leverage the sensors in smartphones, smartwatches, drones, and loT devices, to deliver real-world applications",
  "metadata": {
    "source": "data/2025-2026 Academic Catalog.pdf",
    "doc_type": "pdf",
    "page": 574,
    "section": "",
    "file_hash": "14dada9f1bab",
    "parent_id": "19b9354b-7ab5-5ffc-9069-7f6d5f837e4c"
  }
}