{
  "page_content": "2. Smith School Lower Level Core (C- or higher, regular grading option)\n\n____ MATH120(220) or MATH140 (or MATH130) Calculus I (3/4)\n\n____ BMGT110 Business Value Chain (3) (not required for transfer students)\n\n____ BMGT220 Principles of Accounting I (3)\n\n____ BMGT221 Principles of Accounting II (3)\n\n____ BMGT230 or 231 (or equivalent) Business Statistics (3)\n\n___ (3)\n\n___ (3)\n\n___ (3)\n\n___ (3)\n\nBMGT321 Managerial Acct or BMGT428 Spec Topic in Acct BMGT341 Fin Markets or ECON330 Money & Banking BMGT354 Consumer Analysis or BMGT458 Spec Topic in Mkt BMGT430 Data Modeling in Bus or BMGT438 Spec Topic in OM BMGT446 Int’l Fin or BMGT448 Spec Topic in Fin or ECON305 Int Macro Econ or ECON306 Inter Micro Econ BMGT454 Global Marketing BMGT466 Global Business Strategy or BMGT469 M&O Short- term Study Abroad BMGT477 Int’l SCM or BMGT478 Spec Topic in SCM BMGT485 Project Management (INST453 Project Mgmt for Information Science can sub.) Or a maximum of 1 course (3cr) from ARAB304 Advanced Modern Standard Arabic I CHIN301 Advanced Chinese I FREN301 Composition & Style GERS301 Conv & Comp I: Germ Speaking World HEBR313 Conversation & Composition I ITAL301 Italian Composition JAPN301 Advanced Japanese I PERS301 Advanced Persian I PORT405 Portuguese for Spanish Speakers RUSS301 Advanced Russian I SPAN301 Advanced Grammar & Composition\n\n____ ECON200 Principles of Micro-Economics (3)\n\n____ ECON201 Principles of Macro-Economics (3)\n\nCum Credit Total (18): ______\n\n____ COMM100/107/200 Public Speaking or any GenEd Oral Comm (3)",
  "metadata": {
    "source": "data/International Business - Degree Requirements - 2025.pdf",
    "doc_type": "pdf",
    "page": 1,
    "section": "",
    "file_hash": "b388ad7e6c64",
    "parent_id": "1d298c3c-3272-5a10-a120-8850aa77d113"
  }
}