{
  "page_content": "SURV630 Questionnaire Design and Evaluation (3 Credits) The stages of questionnaire design; developmental interviewing, question writing, question evaluation, pretesting, and questionnaire ordering and formatting. Reviews of the literature on questionnaire construction, the experimental literature on question effects, and the psychological literature on information processing. Examination of the diverse challenges posed by self versus proxy reporting and special attention is paid to the relationship between mode of administration and questionnaire design. Restriction: Must be in the Survey and Data Science Doctoral or Master's Program, or the Applied Political Analytics Master's Program; or permission of the Joint Program in Survey Methodology. Credit Only Granted for: SURV430 and SURV630.\n\nSURV631 Questionnaire Design (2 Credits) This course introduces students to the stages of questionnaire development. The course reviews the scientiﬁc literature on questionnaire construction, the experimental literature on question effects, and the psychological literature on information processing. It will also discuss the diverse challenges posed by self- versus proxy-reporting and special attention is paid to the relationship between mode of administration and questionnaire design. Students will also get hands-on experience in developing their own questionnaire. Restriction: Permission of BSOS-Joint Program in Survey Methodology department.",
  "metadata": {
    "source": "data/2025-2026 Academic Catalog.pdf",
    "doc_type": "pdf",
    "page": 872,
    "section": "",
    "file_hash": "14dada9f1bab",
    "parent_id": "1d67aec3-6bba-5779-8902-8d575af88239"
  }
}