{
  "page_content": "Microbiology 0404D Course\n\nTitle\n\nRequired Courses\n\nBSCI283\n\nBSCI412\n\nPrinciples of Microbiology 1 Microbial Genetics (Lab)\n\nBSCI443\n\nMicrobial Physiology\n\nBiochemistry Courses\n\nBCHM461 & BCHM462\n\nBiochemistry I and Biochemistry II",
  "metadata": {
    "source": "data/computer-mathematical-natural-sciences--biological-sciences.pdf",
    "doc_type": "pdf",
    "page": 5,
    "section": "",
    "file_hash": "21998b61ae3f",
    "parent_id": "210dafc2-2608-5702-85fe-01eae69ca512"
  }
}