{
  "page_content": "Prerequisite: PHYS270 and MATH141.\n\nRecommended: Any MATH 240, MATH 461, MATH341, or ENEE290\n\nor equivalent courses covering linear algebra, eigenvalues, and eigenvectors .\n\nJointly offered with: ENME434.\n\nCredit Only Granted for. ENME434 or ENME692.\n\nENME694 Fundamentals of Optics and Optical Systems for Engineers (3 Credits)\n\nThis unique course is designed to teach the fundamentals of optics\n\nand optical systems for engineering students, more specifically (1) to familiarize students with the optical principles and applications, and (2) to help them learn the method details and develop skills for research and development. The key concepts are presented, with an emphasis\n\non their physical meanings rather than theoretical and mathematical meanings, to help create a better understanding of optics for engineering applications.\n\nCredit Only Granted for. ENME694 or ENME808Z.",
  "metadata": {
    "source": "data/2025-2026 Academic Catalog.pdf",
    "doc_type": "pdf",
    "page": 681,
    "section": "",
    "file_hash": "14dada9f1bab",
    "parent_id": "2367d65d-9504-5b68-9668-a5ddb05a5060"
  }
}