{
  "page_content": "Additional information on developing a graduation plan can be found on the following pages:\n\nhttp://4yearplans.umd.edu\n\nthe Student Academic Success-Degree Completion Policy (https:// academiccatalog.umd.edu/undergraduate/registration-academic- requirements-regulations/academic-advising/#success) section of this catalog",
  "metadata": {
    "source": "data/classics-major.pdf",
    "doc_type": "pdf",
    "page": 2,
    "section": "",
    "file_hash": "7a9f195fa3df",
    "parent_id": "252ba99b-f37d-5dbd-8bf6-1b405c956e44"
  }
}