{
  "page_content": "Agricultural and Extension Education The Agricultural and Extension Education specialization provides students with varying coursework in agribusiness & communications; animal, food & plant sciences; biotechnology; environmental & natural resources; leadership, youth & career development; power, structural & technical systems; and foundational pedagogical education courses. Students practice agricultural literacy techniques throughout their individualized learning experiences to develop mastery in educating using agricultural concepts with diverse audiences. Inclusion within\n\nAgricultural Science and Technology Major\n\n1\n\nthe Terrapin Teachers program provides cross-disciplinary and interdisciplinary opportunities for learning with peers.\n\nGraduates focused on formal education may become certiﬁed secondary high school agricultural teachers in public or private schools or specialize in an area for career technical education. Those focused as agricultural advocates may seek non-formal education jobs in non-proﬁt agricultural literacy based foundations, become Extension youth educators, Extension agricultural specialists, or work within agricultural industry public relations areas. Proximity to federal agencies provides students with an opportunity to expand their international and regulation agency networking skills.",
  "metadata": {
    "source": "data/agricultural-science-technology-major.pdf",
    "doc_type": "pdf",
    "page": 1,
    "section": "",
    "file_hash": "b3d0254f1f6d",
    "parent_id": "27a95fe1-5db2-548c-aea4-70f8f9b85983"
  }
}