{
  "page_content": "Prerequisite: CPBE100.\n\nRestriction: Must be enrolled in College Park Scholars’ Business, Society and the Economy (CPBE) program.\n\nFormerly: CPSP220.\n\nCPBE230 College Park Scholars: Business, Society & the Economy Internship Practicum (1-3 Credits)\n\nSupervised internship project in an area related to business, society and the economy.",
  "metadata": {
    "source": "data/2025-2026 Academic Catalog.pdf",
    "doc_type": "pdf",
    "page": 120,
    "section": "",
    "file_hash": "14dada9f1bab",
    "parent_id": "367beebc-ca0a-566d-a74b-57ba77a8339f"
  }
}