{
  "page_content": "Scholarships and Financial Assistance\n\nThe Ofﬁce of Student Financial Aid (OSFA) administers all types of federal, state, and institutional ﬁnancial assistance programs and, in cooperation with other university ofﬁces, participates in the awarding of scholarships to deserving students. For information, visit: http:// ﬁnancialaid.umd.edu.",
  "metadata": {
    "source": "data/english-language-literature--cinema-media-studies-major.pdf",
    "doc_type": "pdf",
    "page": 2,
    "section": "",
    "file_hash": "c7d6ece64e0c",
    "parent_id": "3b991cf8-9544-5015-8246-f2b04c9502df"
  }
}