{
  "page_content": "Formerly: HESI417.\n\nLGBT - Lesbian Gay Bisexual Transgender Studies\n\nLGBT200 Introduction to Lesbian, Gay, Bisexual, and Transgender Studies (3 Credits)\n\nAn interdisciplinary study of the historical and social contexts of personal, cultural and political aspects of LGBT life. Sources from a variety of fields, such as anthropology, history, psychology, sociology, and women's studies, focusing on writings by and about LGBT people.",
  "metadata": {
    "source": "data/2025-2026 Academic Catalog.pdf",
    "doc_type": "pdf",
    "page": 341,
    "section": "",
    "file_hash": "14dada9f1bab",
    "parent_id": "430ed7bb-813f-5d8b-a068-429cf0b44a6e"
  }
}