{
  "page_content": "AGST275 Fundamentals of Agricultural and Environmental Chemistry (3 Credits)\n\nAn in-depth discussion of chemistry targeted to students enrolled in plant and animal management curricula offered in AGNR. Covers the nomenclature and basic functional groups in organic chemistry, natural products and pesticides. Current practices of crop, agriculture and environmental management and genetic engineering also discussed. Prerequisite: Minimum grade of C- in CHEM131 and CHEM132; and minimum grade of C- in (PLSC110 and PLSC11) or (PLSC112 and PLSC113) or (BSCI160 and BSCI161) or (BSCI170 and BSCI171). Restriction: Must not have completed CHEM104 or CHEM105; and must be in a major within the AGNR-College of Agriculture and Natural Resources; or permission of instructor.\n\nCredit Only Granted for. AGST275 or PLSC275.",
  "metadata": {
    "source": "data/2025-2026 Academic Catalog.pdf",
    "doc_type": "pdf",
    "page": 11,
    "section": "",
    "file_hash": "14dada9f1bab",
    "parent_id": "55d74cc6-1151-5791-adb6-9abedf694fd9"
  }
}