{
  "page_content": "INST367\n\nInnovation and Social Change: Do Good Now\n\nPrototyping and Development Studio\n\n3\n\nAdmission to the Major Students who are accepted to the university and list Technology and Information Design as their preferred major will start directly in our program. Students currently in the university who are interested in declaring Technology and Information Design must complete our Change of Major process (https://ischool.umd.edu/academics/bachelors- programs/change-major/). For more information, please visit the Technology and Information Design website (https://ischool.umd.edu/ academics/bachelors-programs/bachelor-of-arts-in-technology-and- information-design-at-college-park/) or email infodesign@umd.edu.",
  "metadata": {
    "source": "data/technology-info-design-major.pdf",
    "doc_type": "pdf",
    "page": 1,
    "section": "",
    "file_hash": "691be8c1b71c",
    "parent_id": "5cc98068-de8f-52e0-9783-f30a867bd433"
  }
}