{
  "page_content": "GVPT485 Government and Politics of the Middle East (3 Credits) A comparative study of the governmental systems and political processes of Middle Eastern countries, with special emphasis on the problems of nation-building in emergent countries. Prerequisite: GVPT200; and (GVPT282 or GVPT280). Restriction: Must be in Government & Politics program. Credit Only Granted for: GVPT485 or GVPT459E. Formerly: GVPT459E.\n\nGVPT487 Government and Politics of China (3 Credits) Discussion of major issues in the study of the domestic politics of the People's Republic of China. Restriction: Must be in one of the following programs (Government & Politics; Government & Politics: International Relations) ; and junior standing or higher. Credit Only Granted for: GVPT359A or GVPT487. Formerly: GVPT359A.\n\nGVPT600 Professionalization Seminar in Political Science (1 Credit) An introduction to the practices, norms, and expectations of professional political science. Restriction: Must be in Government and Politics (Doctoral) program.\n\nGVPT477 Voting and Participation (3 Credits) A study of the factors that influence individual vote choice and voter participation in the U.S. The course will introduce political science research pertaining to both topics and will engage current controversies over such things as political campaign laws and the various state and federal rules that govern election administration. Prerequisite: GVPT170 and GVPT241. Restriction: Must be in Government & Politics program.",
  "metadata": {
    "source": "data/2025-2026 Academic Catalog.pdf",
    "doc_type": "pdf",
    "page": 730,
    "section": "",
    "file_hash": "14dada9f1bab",
    "parent_id": "60d65353-9aab-5d3f-b0c8-919432a105d3"
  }
}