{
  "page_content": "PERS301\n\nAdvanced Persian I\n\nPORT405\n\nPortuguese for Spanish Speakers\n\nRUSS301\n\nAdvanced Russian I\n\nSPAN301\n\nAdvanced Grammar and Composition I\n\nTotal Credits\n\nIn addition to the major requirements listed above, please see the Roberts H. Smith School of Business under The Colleges and Schools or www.rhsmith.umd.edu (http://www.rhsmith.umd.edu) for a listing of additional Smith School degree requirements that apply to all Smith School majors.\n\nGRADUATION PLANS Click here (https://www.rhsmith.umd.edu/programs/undergraduate/ academics/academic-majors/) for roadmaps for graduation plans in the Robert H. Smith School of Business.\n\nAdditional information on developing a graduation plan can be found on the following pages:\n\nhttp://4yearplans.umd.edu\n\n• the Student Academic Success-Degree Completion Policy (https:// academiccatalog.umd.edu/undergraduate/registration-academic-\n\n1\n\n18\n\n2\n\nInternational Business Major",
  "metadata": {
    "source": "data/international-business-major.pdf",
    "doc_type": "pdf",
    "page": 1,
    "section": "",
    "file_hash": "8ef45e7227ba",
    "parent_id": "697c42db-e696-501f-86ba-332e7b5a3f4a"
  }
}