{
  "page_content": "Select two courses from the Film Criticism category, any rubric Select two courses from the Film Electives category\n\nOption Two:\n\nSelect four courses in Film Electives that create a coherent emphasis 5\n\nTotal Credits\n\n1 Fulﬁlls Gen Ed req. in Humanities. Cinema and Media Studies majors must take ENGL245 (https://academiccatalog.umd.edu/search/? P=ENGL245)/CINE245 (https://academiccatalog.umd.edu/search/? P=CINE245) before they take other 3xx or 4xx-level Cinema and Media Studies courses. We recommend that it be taken no later than sophomore year.\n\n2 Students may take the two courses in any order.\n\n3 At least one course in this category must be taken at the 4xx-level. For a list of courses that will satisfy each sub-category, please see https:// sllc.umd.edu/ﬁelds/cinema-media/courses/.\n\n39\n\n2 Cinema and Media Studies Major (SLLC)\n\n4 Up to two courses in this category may be taken at the 2xx-level. At least one must be taken at the 4xx-level. Please consult the full list of courses accepted for the major: https://sllc.umd.edu/ﬁelds/ cinema-media/courses/ (https://sllc.umd.edu/ﬁelds/cinema-media/ courses/.html).\n\n5 The four courses should be selected in consultation with the Cinema and Media Studies Advisor to allow students to explore a speciﬁc area of interest or an area related to their future academic or professional plans.",
  "metadata": {
    "source": "data/languages-literatures-cultures--cinema-media-studies-major.pdf",
    "doc_type": "pdf",
    "page": 1,
    "section": "",
    "file_hash": "5b0822d194c1",
    "parent_id": "6f6b9e1f-a495-5f6f-887a-34a28f51e056"
  }
}