{
  "page_content": "GEOL100 & GEOL110\n\nPhysical Geology and Physical Geology Laboratory\n\nGEOL120 & GEOL110\n\nEnvironmental Geology and Physical Geology Laboratory\n\nSelect one of the following:\n\n3\n\nASTR330\n\nSolar System Astronomy\n\nPlanetary Sciences Minor (GEOL)",
  "metadata": {
    "source": "data/geology--planetary-sciences-minor.pdf",
    "doc_type": "pdf",
    "page": 1,
    "section": "",
    "file_hash": "cb8c8240b55c",
    "parent_id": "722fa188-ccd9-5853-8e61-c8fa86504a7e"
  }
}