{
  "page_content": "Student Initials_________________\n\nElective 3xx-4xx\n\nNotes:\n\n· Minimum Grade Requirement: Major courses & ENGL 101= C-; Arts and Humanities (ARHU) and General Education = D- . (Subject to change).\n\nSee current catalog for details.\n\n· In order to graduate, you must have at least a 2.0 G.P.A. Students sometimes exceed 120 credits in order to fulfill all graduation requirements.\n\n· If you repeat a course in which you have received at least a “D -”, you will not receive any additional credit.\n\n· **All students must complete two Distributive Studies courses that are approved for I-series courses. The Understanding Plural Societies and Cultural Competence courses may also fulfill Distributive Studies categories.\n\n_________________________________________\n\nName (Please print)\n\n_______________________\n\nUID\n\n(Semester started at UM)\n\nMatriculation date___________________",
  "metadata": {
    "source": "data/IMD_Computing_FourYearPlan.pdf",
    "doc_type": "pdf",
    "page": 1,
    "section": "",
    "file_hash": "72c77c746642",
    "parent_id": "748f30a4-7dfa-5625-9645-5c5d3f977503"
  }
}