{
  "page_content": "CMSC250 Discrete Structures (4 Credits)\n\nFundamental mathematical concepts related to computer science, including finite and infinite sets, relations, functions, and propositional logic. Introduction to other techniques, modeling and solving problems in computer science. Introduction to permutations, combinations, graphs, and trees with selected applications.\n\nPrerequisite: Minimum grade of C- in CMSC131; and minimum grade of C- in MATH141.\n\nRestriction: Must be in a major within the CMNS-Computer Science department; or must be in Engineering: Computer program; or must be\n\nin the Computer Science Minor program; and Permissions of CMSC - Computer Science department.",
  "metadata": {
    "source": "data/2025-2026 Academic Catalog.pdf",
    "doc_type": "pdf",
    "page": 109,
    "section": "",
    "file_hash": "14dada9f1bab",
    "parent_id": "7a29c42d-7d4b-57f4-b604-7d413127528f"
  }
}