{
  "page_content": "in writing, orally, and in performance.\n\n2. Demonstrate growing technical understanding and fluency in dance\n\ntechnique.\n\n3. Participate in the creative process through the creation and\n\ninterpretation of choreography.\n\n4. Apply interdisciplinary research methods to dance scholarship and",
  "metadata": {
    "source": "data/dance-major.pdf",
    "doc_type": "pdf",
    "page": 1,
    "section": "",
    "file_hash": "f693faadccd6",
    "parent_id": "7b3c2dfc-af8d-5846-8e33-420ae99de835"
  }
}