{
  "page_content": "UNIV348 Federal Semester Seminar (3 Credits)\n\nThis topical seminar will approach Federal policy formation through a combination of framework-based and content-specific considerations. Content and themes will vary. The Federal Semester is an offering of the Office of Undergraduate Studies in conjunction with several academic colleges and the University Career Center.\n\nRestriction: Must be in the Federal Semester program; and permission of UGST-Undergraduate Studies; and junior standing or higher.\n\nRepeatable to: 6 credits if content differs.",
  "metadata": {
    "source": "data/2025-2026 Academic Catalog.pdf",
    "doc_type": "pdf",
    "page": 443,
    "section": "",
    "file_hash": "14dada9f1bab",
    "parent_id": "7e519128-243b-5b75-b5be-fba45207afc1"
  }
}