{
  "page_content": "PHPE386 Experiential Learning Practicum in Philosophy, Politics, and Economics (3-6 Credits)\n\nFor students who wish to gain experience working in research outside the classroom. Pending approval of the department, students may work at a professional site or remotely under professional supervision - your primary supervisor must be a professional in the field. Beyond working at a professional site or under professional supervision, students will have to complete further assignments to receive a passing grade in the course. Students may take PHPE386 for three-six credits, but only three credits will count towards the major requirements. PHPE386 is only open to those with junior standing or above.\n\nRestriction: Junior standing or higher.\n\n2025-2026 [updated 2025.04.17]\n\nPHPE400 Individual and Group Decision-Making (3 Credits) Foundational issues that arise within the theories of rational choice that underlie the treatments of decision-making found in economics, politics, and the other social sciences. The course is focused on individual decisions (rational choice theory), strategic decisions (game theory) and group decisions (social choice theory). In addition to presenting the formal models of decision making, we also discuss to what extent these mathematical theories explain social interactions. An important aspect of the course is to introduce students to the ways in which economic analysis has been applied to issues in social and political philosophy. Readings will be drawn from the literature in economics, psychology, statistics and political science, as well as philosophy.\n\nRestriction: Must be in the Philosophy, Politics and Economics major; and must have junior standing or higher; or permission of instructor .",
  "metadata": {
    "source": "data/2025-2026 Academic Catalog.pdf",
    "doc_type": "pdf",
    "page": 374,
    "section": "",
    "file_hash": "14dada9f1bab",
    "parent_id": "7e6b49f2-9b66-5677-87ff-313b2649bdcf"
  }
}