{
  "page_content": "UNIV362 Designing Your Life after College (2 Credits)\n\nHelps students anticipate and prepare for changes in finances, social life, health, and career dynamics they are likely to experience as they transition from college to working full-time. It focuses on understanding what resources students have as they enter the workforce as critical for navigating post-graduation changes successfully. It offers an overview of financial, risk management and professional development approaches to increase students’ confidence regarding post-graduation decisions; in addition, it develops their creative problem solving and reflection skills to help them align the outcomes of their decisions with their values. Restriction: Must have earned a minimum of 60 credits.\n\nUNIV378 Beyond the Classroom Experiential Learning (1-3 Credits) This is the internship component of the Beyond the Classroom program in which students hold internships at organizations such as governmental units and non-profit agencies.",
  "metadata": {
    "source": "data/2025-2026 Academic Catalog.pdf",
    "doc_type": "pdf",
    "page": 443,
    "section": "",
    "file_hash": "14dada9f1bab",
    "parent_id": "82b2c599-3b96-5893-bcaf-72b539aa41c3"
  }
}