{
  "page_content": "Specializations: CEBG, GENB (N–Z), and MICB\n\nDepartment of Cell Biology & Molecular Genetics Undergraduate Ofﬁce 1109 Microbiology Phone: 301-405-2766\n\nUndergraduate Director: Dr. David Straney 3122 Microbiology\n\nPhone: 301-405-1622 straney@umd.edu\n\nSpecialization: GENB (A–M)\n\nDepartment of Entomology Main Ofﬁce 4112 Plant Sciences Building Phone: 301-405-3911\n\nUndergraduate Director: Dr. David Hawthorne 4132 Plant Sciences Building Phone: 301-405-2401 djh@umd.edu",
  "metadata": {
    "source": "data/computer-mathematical-natural-sciences--biological-sciences.pdf",
    "doc_type": "pdf",
    "page": 6,
    "section": "",
    "file_hash": "21998b61ae3f",
    "parent_id": "846ad0c8-24c6-5c9c-b2c9-abcf499c42da"
  }
}