{
  "page_content": "BMGT485 Project Management (3 Credits) Modern project management techniques that are used by modern practicing professionals will be covered. Particular attention is given to the management of technology based systems and projects in a business enterprise. The topics covered include: deﬁning project scope, alignment of projects with enterprise strategy, managing project cost, time and risks using tools such as CPM/PERT, and measuring project performance. Prerequisite: BMGT231 or BMGT230; or students who have taken courses with comparable content may contact the department. Restriction: Must be in a major in BMGT-Robert H. Smith School of Business. Credit Only Granted for: BMGT485, ENCE320, ENCE325, INST408O or INST453.\n\nBMGT487 Six Sigma Innovation (3 Credits) Enhances the overall understanding of Six Sigma Strategy, Tools and Methods to positively influence the performance of a business process, a product or service. Highlights the application of Deﬁne-Measure-Analyze- Improve-Control (DMAIC),Design For Six Sigma (DFSS), and the pursuit of Critical to Quality criteria (CTQ's) in a collaborative perspective, one that recognizes a balance between efﬁciency, and effectiveness and between statistical analysis and statistical thinking. Prerequisite: STAT400, BMGT231, BMGT230, or ENME392.",
  "metadata": {
    "source": "data/2025-2026 Academic Catalog.pdf",
    "doc_type": "pdf",
    "page": 505,
    "section": "",
    "file_hash": "14dada9f1bab",
    "parent_id": "86899b70-64df-5b91-a89f-774d690eb947"
  }
}