{
  "page_content": "GERS315\n\nPracticum in Translation I\n\nGERS319\n\nSelected Topics in German Language Studies\n\nGERS402\n\nAdvanced Conversation and Composition\n\nGERS419\n\nSelected Topics in German Language Studies\n\nGERS473\n\nVariation in Contemporary German Language\n\nSelect a minimum of 6 credits of the following literature courses:",
  "metadata": {
    "source": "data/german-studies-major.pdf",
    "doc_type": "pdf",
    "page": 1,
    "section": "",
    "file_hash": "0174f4acbd3a",
    "parent_id": "8f3147a0-7131-591d-8cab-72daa4a24c45"
  }
}