{
  "page_content": "Academic Regulations\n\nCourse Numbering System\n\nThe first digit of the course number designates the level of the course and the last two digits identify the course. Courses ending with the numeral 8 or 9 are the only courses that are repeatable for credit. Course levels are designated as follows:\n\n000-099 Non-credit courses\n\n100-199 Courses primarily for first-year students\n\n200-299 Courses primarily for sophomore students\n\n300-399 Junior/Senior courses (not acceptable for credit toward graduate degrees)\n\n400-499 Junior/Senior courses (acceptable for credit toward some graduate degrees)\n\n500-599 Professional School courses (Dentistry, Law, Medicine) or post baccalaureate courses (not for graduate degree credit)\n\n600-899 Courses restricted to graduate students\n\n799 Masters Thesis credit\n\n899 Doctoral Dissertation credit",
  "metadata": {
    "source": "data/registration_guide.pdf",
    "doc_type": "pdf",
    "page": 25,
    "section": "",
    "file_hash": "d466994ef761",
    "parent_id": "91f1094f-759f-52c1-b78f-65868014eef9"
  }
}