{
  "page_content": "C. Standard of Proof\n\nStudents seeking in#state status shall have the burden of proving by clear and convincing evidence that they satisfy the requirements and standards set forth in this Policy. Assignment of in#state or out#of#state status will be made by each USM institution upon a review of the totality of facts known by the institution or presented to it by the student.",
  "metadata": {
    "source": "data/university-policies.pdf",
    "doc_type": "pdf",
    "page": 5,
    "section": "",
    "file_hash": "d41e70b3bf07",
    "parent_id": "9325e19e-e439-5a21-be79-d3c61ec079b4"
  }
}