{
  "page_content": "Admission to the Major\n\nIncoming students who wish to enter ENSP may do so by selecting ENSP- Undeclared on their application for admission. On-campus students may declare ENSP during a meeting with the Assistant Director. Please review the ENSP website at http://ensp.umd.edu to learn about the program and its requirements prior to your ﬁrst advising meeting.",
  "metadata": {
    "source": "data/environmental-science-policy-major.pdf",
    "doc_type": "pdf",
    "page": 1,
    "section": "",
    "file_hash": "54fda76108cf",
    "parent_id": "93bf48f0-5890-53a9-b894-22c57591078a"
  }
}