{
  "page_content": "Before You Register\n\nUndergraduate Students\n\nCurrent Undergraduate Students: Currently enrolled undergraduate students receive a notification email with information about early registration and a link to check their registration appointment time and registration blocks. Registration appointments for the fall semester are scheduled from late March through early May, and appointments for the spring semester are scheduled from late October through early December. Students may register at their scheduled registration appointment time or any time thereafter.\n\nIf you are a degree candidate you will not receive an appointment email. If you wish to register for the next semester, call 301-314-8240 to request an appointment.",
  "metadata": {
    "source": "data/registration_guide.pdf",
    "doc_type": "pdf",
    "page": 6,
    "section": "",
    "file_hash": "d466994ef761",
    "parent_id": "a2296586-2f39-5808-96de-03b86dd6a45b"
  }
}