{
  "page_content": "SOCIOLOGY MAJOR\n\nProgram Director: Nicole DeLoatch, Ph.D.\n\nSociology is the scientiﬁc study of society and its institutions, organizations, and groups. By observing the broad range of activities in society, and exploring topics such as social class, race, gender, deviance, family, religion, the workplace, and demographic trends, sociologists provide important information and perspectives on our social order and the causes and impacts of social change. Sociology provides important information useful both to personal life and public policy decisions. Sociology is among the broadest of the social sciences and is characterized by considerable pluralism in theoretical and methodological approaches, substantive specializations, and in units of analysis.",
  "metadata": {
    "source": "data/sociology-major.pdf",
    "doc_type": "pdf",
    "page": 1,
    "section": "",
    "file_hash": "946e45293c97",
    "parent_id": "a477e639-bb3a-56e2-9782-c1a7e7189112"
  }
}