{
  "page_content": "THEX102 London: Walking the City (3 Credits) What is a city? This course asks students to consider the different ways that we might deﬁne a city and to explore different perspectives on London inflected by mobility, migration, class and gender. Through reading a range of literary and theoretical texts, as well as walking lectures, students will develop an understanding of the role of literature, performance and cultural institutions in producing and contesting urban experience. Additional Information: This course is offered as part of the Arts & Humanities-in-London study abroad program. Students must apply for this program through Education Abroad: More information at https:// globalmaryland.umd.edu/ofﬁces/education-abroad/program/11854. Education Abroad processes registrations for this course on behalf of students.\n\nTHEX300 Race and Racism in Performance (3 Credits) Explores how race is performed in theater, art, and popular culture. Examines questions about racism in performance casting and practices. Additional Information: This course is offered as part of the Arts & Humanities-in-London study abroad program. Students must apply for this program through Education Abroad: More information at https:// globalmaryland.umd.edu/ofﬁces/education-abroad/program/11854. Education Abroad processes registrations for this course on behalf of students.",
  "metadata": {
    "source": "data/2025-2026 Academic Catalog.pdf",
    "doc_type": "pdf",
    "page": 433,
    "section": "",
    "file_hash": "14dada9f1bab",
    "parent_id": "ab2619bc-bd97-5975-a6a9-0f598fdf0c10"
  }
}