{
  "page_content": "Additional Information: Not applicable to MATH/STAT major or minor requirements.\n\nMATH484 Geometry for High School Teachers (3 Credits)\n\nFocuses on concepts related to geometry, including several geometry axiom schemes, transformations, and similarity. Includes constructions with Geometer’s Sketchpad.\n\nPrerequisite: MATH141; or students who have taken courses with comparable content may contact the department.",
  "metadata": {
    "source": "data/2025-2026 Academic Catalog.pdf",
    "doc_type": "pdf",
    "page": 796,
    "section": "",
    "file_hash": "14dada9f1bab",
    "parent_id": "b2640d44-27e3-5d9e-a46a-fd50bc813874"
  }
}