{
  "page_content": "GRADUATION PLANS\n\nClick here (https://www.arhu.umd.edu/academics/advising/academic- plans/) for roadmaps for graduation plans in the College of Arts and Humanities.\n\nAdditional information on developing a graduation plan can be found on the following pages:\n\n• http://4yearplans.umd.edu\n\n• the Student Academic Success-Degree Completion Policy (https:// academiccatalog.umd.edu/undergraduate/registration-academic- requirements-regulations/academic-advising/#success) section of this catalog",
  "metadata": {
    "source": "data/linguistics-major.pdf",
    "doc_type": "pdf",
    "page": 2,
    "section": "",
    "file_hash": "3b8a5c1df4bc",
    "parent_id": "bd18e8fc-c51e-53f4-b39c-b1e376c0a4b7"
  }
}