{
  "page_content": "appropriate learning strategies.\n\nREQUIREMENTS Prior Study Prior to being admitted to the Biocomputational Engineering major, students should have completed basic math/science/engineering courses, lower-level general education requirements (or an associate's degree from a Maryland public institution), and 60 credits.",
  "metadata": {
    "source": "data/biocomputational-engineering.pdf",
    "doc_type": "pdf",
    "page": 1,
    "section": "",
    "file_hash": "9c4f0b41e173",
    "parent_id": "c02d6c3b-7700-5fa0-8f5f-b2a321131c48"
  }
}