{
  "page_content": "Technology Socialprenuer (The Technology Socialpreneur)\n\nTotal Credits\n\nADVISING Admission and advising for the Technology Innovation Leadership minor is managed by the UMD Information Science undergraduate team at the Universities at Shady Grove campus (Rockville, MD).\n\nPlease note that advising questions related to how the Minor courses may count towards degree requirements or other program requirements should be directed to a student’s academic advisor.\n\nIf you have any questions about this minor, please email usginfosci@umd.edu.\n\n1",
  "metadata": {
    "source": "data/technology-innovation-leadership-minor.pdf",
    "doc_type": "pdf",
    "page": 1,
    "section": "",
    "file_hash": "b9174f684083",
    "parent_id": "c7331e8a-300f-5ee1-b93d-99a528bb1500"
  }
}