{
  "page_content": "You have reached 30 credits (earned + currently registered for) and have not completed a math course that meets the fundamental studies requirement. If you are currently enrolled in a course that will meet the requirement, the block will be lifted after you have earned credit.\n\nAcademic advising college to see if you may be eligible for an exception which will allow you to register using Testudo OR register in person with the Office of the University Registrar. Your registration must include a course that meets this requirement\n\nNew student requires advising\n\nNewly admitted students must attend a new student orientation program. You will receive advising and will register for classes during the program.",
  "metadata": {
    "source": "data/registration_guide.pdf",
    "doc_type": "pdf",
    "page": 8,
    "section": "",
    "file_hash": "d466994ef761",
    "parent_id": "c94ef4ca-76dc-5132-92f5-d1a1c2d0307d"
  }
}