{
  "page_content": "642 ENCH - Engineering, Chemical\n\nENCE743 Soil Dynamics and Earthquake Engineering (3 Credits)\n\nReview of theory of vibration and wave propagation in elastic media. Field and laboratory methods for determining dynamic soil properties. Analysis and design of soil-foundation systems subjected to machinery generated vibrations and methods of foundation isolation. Earthquake causes, magnitude and intensity, seismic hazard evaluation, NEHRP site classification, site response analyses and ground motion amplification, liquefaction and response of earth structures.",
  "metadata": {
    "source": "data/2025-2026 Academic Catalog.pdf",
    "doc_type": "pdf",
    "page": 642,
    "section": "",
    "file_hash": "14dada9f1bab",
    "parent_id": "cd966da6-8d3a-51e3-96fd-b25900148acc"
  }
}