{
  "page_content": "AMST856 Museum Research Seminar (3 Credits)\n\nA research seminar focusing on the practice and presentation of cultural and historical scholarship in museums and historical sites. Students will complete an original research project on the challenges and opportunities of public exhibition and interpretation of cultural and historical research. Prerequisite: AMST655, ANTH655, or HIST610.\n\nCross-listed with: ANTH856, HIST810, INST786.\n\nCredit Only Granted for. AMST856, ANTH856, HIST810, INST728U or INST786.",
  "metadata": {
    "source": "data/2025-2026 Academic Catalog.pdf",
    "doc_type": "pdf",
    "page": 462,
    "section": "",
    "file_hash": "14dada9f1bab",
    "parent_id": "ce7cce3d-64e6-5d4c-adea-76e82a96cf3e"
  }
}