{
  "page_content": "ENST - Environmental Science and Technology\n\nENST403 Invasive Species Ecology (3 Credits) We will examine ecological, evolutionary, and anthropogenic processes facilitating or resisting biological invasions, and consider their environmental, economic, and human health impacts. We will consider various management strategies to mitigate invasions and identify areas of future research. Field trips and detailed discussion of recent ﬁndings and controversies in the literature will help illustrate fundamental concepts of invasions among various ecosystems. Credit Only Granted for: ENST403, ENST603, or ENST689R.\n\nENST404 Ecological and Natural Resources Ethics (3 Credits) Bridges science and management with ethical theory and concepts to help scientists, regulators, and managers understand how to deal with potential ethical dilemmas that arise in natural resource and environmental management implementation and policy development. Prerequisite: ENST214 and ENST360. Recommended: ENST314, ENST410, and ENST460. Restriction: Senior standing or higher. Jointly offered with ENST604. Credit Only Granted for: ENST604 or ENST404.",
  "metadata": {
    "source": "data/2025-2026 Academic Catalog.pdf",
    "doc_type": "pdf",
    "page": 694,
    "section": "",
    "file_hash": "14dada9f1bab",
    "parent_id": "cf7fefc9-4d56-58d0-a6fb-b23a73330b97"
  }
}