{
  "page_content": "BSOS233 Data Science for the Social Sciences (3 Credits) An introduction to modern methods of data analysis for social scientists. This course emphasizes teaching students who have no previous coding experience how to analyze data and extract meaning in a social science context. Students will gain critical programming skills and learn inferential thinking through examples and projects with real-world relevance. Prerequisite: Must have completed or be concurrently enrolled in STAT 100. Restriction: Must be in a major in the College of Behavioral and Social Sciences or the College of Information Studies; or permission of instructor.\n\nBSOS238 Special Topics in Study Abroad II (1-6 Credits) Special topics course taken as part of an approved study abroad program. Repeatable to: 15 credits if content differs.",
  "metadata": {
    "source": "data/2025-2026 Academic Catalog.pdf",
    "doc_type": "pdf",
    "page": 80,
    "section": "",
    "file_hash": "14dada9f1bab",
    "parent_id": "d1dfb48f-c744-5ed2-806f-7877fc6660fb"
  }
}