{
  "page_content": "PHYS612 Quantum and Statistical Physics I (4 Credits) First course of a two-semester graduate level sequence on topics in quantum mechanics and statistical mechanics. Prerequisite: Must have an outstanding undergraduate background in physics. Restriction: Permission of CMNS-Physics Department.\n\nCourses in 2025-2026 Academic Catalog - DRAFT COPY\n\nPHYS613 Quantum and Statistical Physics II (4 Credits) Second course of a two-semester graduate level sequence on topics in quantum mechanics and statistical mechanics. Prerequisite: PHYS612; or permission of instructor. Restriction: Permission of the Physics Department.\n\nPHYS615 Nonlinear Dynamics of Extended Systems (3 Credits) Theory and applications of nonlinear dynamics of extended systems including nonlinear waves, pattern formation, turbulence, self-organized criticality and networks. Additional topics to be selected by instructor from areas of current research. Prerequisite: PHYS601.\n\nPHYS622 Introduction to Quantum Mechanics I (4 Credits) First and second semesters. A study of the Schroedinger equation, matrix formulations of quantum mechanics, approximation methods, scattering theory, etc. Applications to solid state, atomic, and nuclear physics. Prerequisite: Must have an outstanding undergraduate background in physics.",
  "metadata": {
    "source": "data/2025-2026 Academic Catalog.pdf",
    "doc_type": "pdf",
    "page": 826,
    "section": "",
    "file_hash": "14dada9f1bab",
    "parent_id": "d9397d8b-9e24-5f9f-8806-2b8cee292292"
  }
}