{
  "page_content": "Prerequisite: ENES220; and permission of ENGR-Civil & Environmental Engineering department.\n\nCourses in 2025-2026 Academic Catalog - DRAFT COPY 159\n\nENCE342 Structural Analysis and Design | (3 Credits)\n\nProvides an introduction to structural analysis, focusing on the behavior of statically determinate and indeterminate structures. Students will learn how to analyze structural systems under various loading conditions and explore real-world examples of structural failures. A key component of the course is the introduction of Python as a computational tool for structural analysis. The course will also cover foundational concepts in structural mechanics, such as the analysis of trusses, beams, frames, arches, and cable structures, preparing students for more advanced structural design in later courses.\n\nPrerequisite: Minimum grade of C- in ENES220 and ENCE203. Restriction: Permission of the ENGR-Civil & Environmental Engineering Department.",
  "metadata": {
    "source": "data/2025-2026 Academic Catalog.pdf",
    "doc_type": "pdf",
    "page": 159,
    "section": "",
    "file_hash": "14dada9f1bab",
    "parent_id": "e3128fb2-12bc-5217-a52e-c4d3c93d8987"
  }
}