{
  "page_content": "3. An ability to communicate effectively with a range of audiences.\n\n4. An ability to recognize ethical and professional responsibilities in\n\nengineering situations and make informed judgments, which must consider the impact of engineering solutions in global, economic, environmental, and societal contexts.\n\n5. An ability to function effectively on a team whose members together provide leadership, create a collaborative and inclusive environment, establish goals, plan tasks, and meet objectives.\n\n6. An ability to develop and conduct appropriate experimentation,\n\nanalyze and interpret data, and use engineering judgment to draw conclusions.\n\n7. An ability to acquire and apply new knowledge as needed, using",
  "metadata": {
    "source": "data/bioengineering-major.pdf",
    "doc_type": "pdf",
    "page": 1,
    "section": "",
    "file_hash": "a1f746c495da",
    "parent_id": "e5894e52-57a8-55f4-ae53-3116def94366"
  }
}