{
  "page_content": "Credits\n\n18-19\n\n12-14\n\nGEOL100\n\nPhysical Geology\n\n& GEOL110\n\nand Physical Geology Laboratory\n\nGEOL120\n\nEnvironmental Geology\n\n& GEOL110\n\nand Physical Geology Laboratory\n\nGroup 4 - Economics:\n\nAREC240\n\nIntroduction to Economics and the Environment\n\nAREC241\n\nEnvironment, Economics and Policy\n\nECON200\n\nPrinciples of Microeconomics\n\nGroup 5 - Geography:\n\nEnvironmental Science and Policy Major",
  "metadata": {
    "source": "data/environmental-science-policy-major.pdf",
    "doc_type": "pdf",
    "page": 1,
    "section": "",
    "file_hash": "54fda76108cf",
    "parent_id": "eb1c44ea-2833-5457-8ec7-e4f324648878"
  }
}