{
  "page_content": "Course\n\nSelect 6 credits of Japanese language courses:\n\nSelect one Japanese linguistics course:\n\nSelect one Japanese literature/cultural studies course:\n\nSelect one additional 3 credit course from the lists above.\n\nTotal Credits\n\n• At least nine of the ﬁfteen hours must be at the 3xx or 4xx level.\n\n• Students must receive a \"C-\" or better in all courses used for the minor.\n\n• An overall GPA of 2.0 in the minor is required for graduation.\n\nJapanese Minor 1\n\n• No more than 6 of the 15 credits toward the minor may be taken at an institution other than UMCP.",
  "metadata": {
    "source": "data/japanese-minor.pdf",
    "doc_type": "pdf",
    "page": 1,
    "section": "",
    "file_hash": "c7ffd55c46f0",
    "parent_id": "f44cb8b0-2716-567e-8f98-7c7e90248e1b"
  }
}