{
  "page_content": "Credit Only Granted for: TLPL288T or TLPL287.\n\nFormerly: TLPL288T.\n\nTLPL288 Special Problems in Education (1-6 Credits)\n\nSpecial and intensive treatment of current topics and issues in teaching, learning, policy and leadership. Available only to freshmen and sophomore students who have definite plans for individual study of approved problems relative to their preparation for teaching. Restriction: Permission of EDUC-Teaching and Learning, Policy and Leadership department.",
  "metadata": {
    "source": "data/2025-2026 Academic Catalog.pdf",
    "doc_type": "pdf",
    "page": 435,
    "section": "",
    "file_hash": "14dada9f1bab",
    "parent_id": "fff0f325-3fc7-5227-b33d-e00cfee163ab"
  }
}